tensorrt_dispatch_libs/__init__.py
tensorrt_dispatch_libs/libnvinfer_dispatch.so.10
tensorrt_dispatch_cu13_libs-10.15.1.29.dist-info/LICENSE.txt
tensorrt_dispatch_cu13_libs-10.15.1.29.dist-info/METADATA
tensorrt_dispatch_cu13_libs-10.15.1.29.dist-info/WHEEL
tensorrt_dispatch_cu13_libs-10.15.1.29.dist-info/top_level.txt
tensorrt_dispatch_cu13_libs-10.15.1.29.dist-info/zip-safe
tensorrt_dispatch_cu13_libs-10.15.1.29.dist-info/RECORD
